setup.py
otlichno/__init__.py
otlichno.egg-info/PKG-INFO
otlichno.egg-info/SOURCES.txt
otlichno.egg-info/dependency_links.txt
otlichno.egg-info/not-zip-safe
otlichno.egg-info/requires.txt
otlichno.egg-info/top_level.txt