Metadata-Version: 1.1
Name: otlichno
Version: 0.0.1
Summary: otlichno package
Home-page: https://www.google.com.ua/?q=django
Author: hellraiser
Author-email: hellraiser@ukr.net
License: BSD
Keywords: otlichno
Platform: UNKNOWN
Classifier: Programming Language :: Python :: 2
Classifier: Programming Language :: Python :: 3
